valuator/__init__.py
valuator/valuator.py
valuator-1.1.3.dist-info/METADATA
valuator-1.1.3.dist-info/WHEEL
valuator-1.1.3.dist-info/top_level.txt
valuator-1.1.3.dist-info/RECORD
