Metadata-Version: 2.4
Name: valuator
Version: 1.1.3
Summary: A lightweight library to fetch and search AI model pricing data
Author: Vikas Konaparthi
Author-email: vikaskonaparthi@gmail.com
Classifier: Programming Language :: Python :: 3
Classifier: License :: OSI Approved :: MIT License
Classifier: Operating System :: OS Independent
Requires-Python: >=3.8
Requires-Dist: aiohttp>=3.8.0
Dynamic: author
Dynamic: author-email
Dynamic: classifier
Dynamic: description
Dynamic: description-content-type
Dynamic: requires-dist
Dynamic: requires-python
Dynamic: summary
